{"status":200,"success":true,"data":{"id":"UWLMacR","deletehash":"","account_id":null,"account_url":null,"ad_type":null,"ad_url":null,"title":"Nothofagus dombeyi","description":"author:Awo\nlicense:CC0\nosmid:node/10224794904","name":"","type":"image/jpeg","width":1285,"height":2285,"size":870268,"views":0,"section":null,"vote":null,"bandwidth":0,"animated":false,"favorite":false,"in_gallery":false,"in_most_viral":false,"has_sound":false,"is_ad":false,"nsfw":null,"link":"https://i.imgur.com/UWLMacR.jpeg","tags":[],"datetime":1669693369,"mp4":"","hls":""}}