{"status":200,"success":true,"data":{"id":"wFis51V","deletehash":"","account_id":null,"account_url":null,"ad_type":null,"ad_url":null,"title":"Hydrant","description":"author:APneunzehn74\nlicense:CC0\nosmid:node/8267713396","name":"","type":"image/jpeg","width":2000,"height":1496,"size":846247,"views":0,"section":null,"vote":null,"bandwidth":0,"animated":false,"favorite":false,"in_gallery":false,"in_most_viral":false,"has_sound":false,"is_ad":false,"nsfw":null,"link":"https://i.imgur.com/wFis51V.jpeg","tags":[],"datetime":1713892959,"mp4":"","hls":""}}