{"status":200,"success":true,"data":{"id":"OUKzIZV","deletehash":"","account_id":null,"account_url":null,"ad_type":null,"ad_url":null,"title":"Obra de arte","description":"author:Awo\nlicense:CC0\nosmid:node/11054163385","name":"","type":"image/jpeg","width":1707,"height":3108,"size":447409,"views":0,"section":null,"vote":null,"bandwidth":0,"animated":false,"favorite":false,"in_gallery":false,"in_most_viral":false,"has_sound":false,"is_ad":false,"nsfw":null,"link":"https://i.imgur.com/OUKzIZV.jpeg","tags":[],"datetime":1689745818,"mp4":"","hls":""}}