{"status":200,"success":true,"data":{"id":"G0Taoib","deletehash":"","account_id":null,"account_url":null,"ad_type":null,"ad_url":null,"title":"Disabled Parking Space","description":"author:5R-MFT\r\nlicense:CC-BY-SA 4.0\r\nosmid:node/11260072207","name":"","type":"image/jpeg","width":1562,"height":2774,"size":857960,"views":0,"section":null,"vote":null,"bandwidth":0,"animated":false,"favorite":false,"in_gallery":false,"in_most_viral":false,"has_sound":false,"is_ad":false,"nsfw":null,"link":"https://i.imgur.com/G0Taoib.jpeg","tags":[],"datetime":1697205054,"mp4":"","hls":""}}