{"status":200,"success":true,"data":{"id":"jdoiKGT","deletehash":"","account_id":null,"account_url":null,"ad_type":null,"ad_url":null,"title":"Bench","description":"author:5R-MFT\r\nlicense:CC-BY-SA 4.0\r\nosmid:node/11534866308","name":"","type":"image/jpeg","width":2774,"height":1562,"size":920197,"views":0,"section":null,"vote":null,"bandwidth":0,"animated":false,"favorite":false,"in_gallery":false,"in_most_viral":false,"has_sound":false,"is_ad":false,"nsfw":null,"link":"https://i.imgur.com/jdoiKGT.jpeg","tags":[],"datetime":1705779760,"mp4":"","hls":""}}