[{"id":140916263,"type":"Feature","geometry":{"type":"Polygon","coordinates":[[[-92.8986606,44.9456661],[-92.7263182,44.9456661],[-92.7263182,44.9644119],[-92.8986606,44.9644119],[-92.8986606,44.9456661]]]},"properties":{"check_user":null,"reasons":[],"tags":[],"features":[],"user":"noliver","uid":"91568","editor":"MapComplete 0.31.2","comment":"Adding data with #MapComplete for theme #charging_stations","comments_count":0,"source":"Not reported","imagery_used":"Not reported","date":"2023-09-06T23:18:32Z","reviewed_features":[],"tag_changes":{},"create":0,"modify":3,"delete":0,"area":0.00323069616192094,"is_suspect":false,"harmful":null,"checked":false,"check_date":null,"host":"https://mapcomplete.org/charging_stations.html","theme":"charging_stations","answer":4,"locale":"en","id":140916263}},{"id":140916188,"type":"Feature","geometry":{"type":"Polygon","coordinates":[[[-92.8986606,44.9456661],[-92.8986606,44.9456661],[-92.8986606,44.9456661],[-92.8986606,44.9456661],[-92.8986606,44.9456661]]]},"properties":{"check_user":null,"reasons":[],"tags":[],"features":[],"user":"noliver","uid":"91568","editor":"MapComplete 0.31.2","comment":"Adding data with #MapComplete for theme #charging_stations","comments_count":0,"source":"Not reported","imagery_used":"Not reported","date":"2023-09-06T23:11:55Z","reviewed_features":[],"tag_changes":{},"create":0,"modify":5,"delete":0,"area":0,"is_suspect":false,"harmful":null,"checked":false,"check_date":null,"host":"https://mapcomplete.org/charging_stations.html","theme":"charging_stations","answer":8,"locale":"en","id":140916188}},{"id":140914125,"type":"Feature","geometry":{"type":"Polygon","coordinates":[[[4.3063571,50.8716459],[4.3074804,50.8716459],[4.3074804,50.8732457],[4.3063571,50.8732457],[4.3063571,50.8716459]]]},"properties":{"check_user":null,"reasons":[],"tags":[],"features":[],"user":"Thierry1030","uid":"286563","editor":"MapComplete 0.31.2","comment":"Adding data with #MapComplete for theme #cyclestreets","comments_count":0,"source":"Not reported","imagery_used":"Not reported","date":"2023-09-06T21:35:06Z","reviewed_features":[],"tag_changes":{},"create":0,"modify":1,"delete":0,"area":0.00000179705534000213,"is_suspect":false,"harmful":null,"checked":false,"check_date":null,"host":"https://mapcomplete.org/cyclestreets.html","theme":"cyclestreets","answer":1,"locale":"fr","id":140914125}},{"id":140913462,"type":"Feature","geometry":{"type":"Polygon","coordinates":[[[-73.216113,-39.8092326],[-73.2160534,-39.8092326],[-73.2160534,-39.8087191],[-73.216113,-39.8087191],[-73.216113,-39.8092326]]]},"properties":{"check_user":null,"reasons":[],"tags":[],"features":[],"user":"Awo","uid":"196556","editor":"MapComplete 0.31.2","comment":"Adding data with #MapComplete for theme #trees","comments_count":0,"source":"Not reported","imagery_used":"Not reported","date":"2023-09-06T21:07:28Z","reviewed_features":[],"tag_changes":{},"create":0,"modify":2,"delete":0,"area":3.06046000003102e-8,"is_suspect":false,"harmful":null,"checked":false,"check_date":null,"host":"https://mapcomplete.osm.be/trees.html","theme":"trees","answer":2,"locale":"es","id":140913462}},{"id":140909762,"type":"Feature","geometry":{"type":"Polygon","coordinates":[[[3.3630898,50.8020428],[3.3630898,50.8020428],[3.3630898,50.8020428],[3.3630898,50.8020428],[3.3630898,50.8020428]]]},"properties":{"check_user":null,"reasons":[],"tags":[],"features":[],"user":"vjyblauw","uid":"2844254","editor":"MapComplete 0.31.2","comment":"Adding data with #MapComplete for theme #benches","comments_count":0,"source":"Not reported","imagery_used":"Not reported","date":"2023-09-06T19:31:26Z","reviewed_features":[],"tag_changes":{},"create":0,"modify":1,"delete":0,"area":0,"is_suspect":false,"harmful":null,"checked":false,"check_date":null,"host":"https://mapcomplete.org/benches.html","theme":"benches","locale":"nl","add-image":1,"id":140909762}},{"id":140909446,"type":"Feature","geometry":{"type":"Polygon","coordinates":[[[3.3720101,50.789632],[3.3720101,50.789632],[3.3720101,50.789632],[3.3720101,50.789632],[3.3720101,50.789632]]]},"properties":{"check_user":null,"reasons":[],"tags":[],"features":[],"user":"vjyblauw","uid":"2844254","editor":"MapComplete 0.31.2","comment":"Adding data with #MapComplete for theme #maps","comments_count":0,"source":"Not reported","imagery_used":"Not reported","date":"2023-09-06T19:22:50Z","reviewed_features":[],"tag_changes":{},"create":0,"modify":1,"delete":0,"area":0,"is_suspect":false,"harmful":null,"checked":false,"check_date":null,"host":"https://mapcomplete.org/maps.html","theme":"maps","locale":"nl","add-image":1,"id":140909446}},{"id":140909233,"type":"Feature","geometry":{"type":"Polygon","coordinates":[[[13.7011375,51.0429735],[13.7011517,51.0429735],[13.7011517,51.0431015],[13.7011375,51.0431015],[13.7011375,51.0429735]]]},"properties":{"check_user":null,"reasons":[{"id":40,"name":"New mapper"}],"tags":[],"features":[],"user":"Semibuilder","uid":"3775220","editor":"MapComplete 0.31.2","comment":"Adding data with #MapComplete for theme #charging_stations","comments_count":0,"source":"Not reported","imagery_used":"Not reported","date":"2023-09-06T19:16:34Z","reviewed_features":[],"tag_changes":{},"create":0,"modify":3,"delete":0,"area":1.81760000004627e-9,"is_suspect":true,"harmful":null,"checked":false,"check_date":null,"host":"https://mapcomplete.org/charging_stations.html","theme":"charging_stations","answer":3,"locale":"de-DE","id":140909233}},{"id":140908822,"type":"Feature","geometry":{"type":"Polygon","coordinates":[[[13.6983407,51.0482126],[13.6983407,51.0482126],[13.6983407,51.0482126],[13.6983407,51.0482126],[13.6983407,51.0482126]]]},"properties":{"check_user":null,"reasons":[{"id":40,"name":"New mapper"}],"tags":[],"features":[],"user":"Semibuilder","uid":"3775220","editor":"MapComplete 0.31.2","comment":"Adding data with #MapComplete for theme #waste","comments_count":0,"source":"Not reported","imagery_used":"Not reported","date":"2023-09-06T19:03:32Z","reviewed_features":[],"tag_changes":{},"create":0,"modify":1,"delete":0,"area":0,"is_suspect":true,"harmful":null,"checked":false,"check_date":null,"host":"https://mapcomplete.org/waste.html","theme":"waste","answer":2,"locale":"de-DE","id":140908822}},{"id":140908491,"type":"Feature","geometry":{"type":"Polygon","coordinates":[[[5.5895647,50.6346648],[5.5895647,50.6346648],[5.5895647,50.6346648],[5.5895647,50.6346648],[5.5895647,50.6346648]]]},"properties":{"check_user":null,"reasons":[],"tags":[],"features":[],"user":"plicploc","uid":"75871","editor":"MapComplete 0.31.2","comment":"Adding data with #MapComplete for theme #cyclofix","comments_count":0,"source":"Not reported","imagery_used":"Not reported","date":"2023-09-06T18:53:14Z","reviewed_features":[],"tag_changes":{},"create":1,"modify":0,"delete":0,"area":0,"is_suspect":false,"harmful":null,"checked":false,"check_date":null,"host":"https://mapcomplete.org/cyclofix","theme":"cyclofix","locale":"fr","change_over_5000m":1,"id":140908491}},{"id":140907103,"type":"Feature","geometry":{"type":"Polygon","coordinates":[[[3.2078945,44.1945157],[3.2078945,44.1945157],[3.2078945,44.1945157],[3.2078945,44.1945157],[3.2078945,44.1945157]]]},"properties":{"check_user":null,"reasons":[],"tags":[],"features":[],"user":"Pieter Vander Vennet","uid":"3818858","editor":"MapComplete 0.31.2","comment":"Adding data with #MapComplete for theme #artwork","comments_count":0,"source":"Not reported","imagery_used":"Not reported","date":"2023-09-06T18:17:45Z","reviewed_features":[],"tag_changes":{},"create":0,"modify":2,"delete":0,"area":0,"is_suspect":false,"harmful":null,"checked":false,"check_date":null,"host":"https://mapcomplete.org/artwork.html","theme":"artwork","locale":"nl","add-image":2,"change_within_25m":2,"id":140907103}},{"id":140906870,"type":"Feature","geometry":{"type":"Polygon","coordinates":[[[3.3539368,50.7605849],[3.4011617,50.7605849],[3.4011617,50.8140548],[3.3539368,50.8140548],[3.3539368,50.7605849]]]},"properties":{"check_user":null,"reasons":[],"tags":[],"features":[],"user":"vjyblauw","uid":"2844254","editor":"MapComplete 0.31.2","comment":"Adding data with #MapComplete for theme #https://raw.githubusercontent.com/seppesantens/MapComplete-Themes/main/cyclenodenetworks/cyclenodenetworks.json","comments_count":0,"source":"Not reported","imagery_used":"Not reported","date":"2023-09-06T18:12:46Z","reviewed_features":[],"tag_changes":{},"create":0,"modify":6,"delete":0,"area":0.00252511068051014,"is_suspect":false,"harmful":null,"checked":false,"check_date":null,"host":"https://mapcomplete.org/theme.html","theme":"https://raw.githubusercontent.com/seppesantens/MapComplete-Themes/main/cyclenodenetworks/cyclenodenetworks.json","locale":"nl","add-image":6,"id":140906870}},{"id":140906815,"type":"Feature","geometry":{"type":"Polygon","coordinates":[[[3.2080157,44.1906594],[3.2272043,44.1906594],[3.2272043,44.1957037],[3.2080157,44.1957037],[3.2080157,44.1906594]]]},"properties":{"check_user":null,"reasons":[],"tags":[],"features":[],"user":"Pieter Vander Vennet","uid":"3818858","editor":"MapComplete 0.31.2","comment":"Adding data with #MapComplete for theme #climbing","comments_count":0,"source":"Not reported","imagery_used":"Not reported","date":"2023-09-06T18:11:12Z","reviewed_features":[],"tag_changes":{},"create":0,"modify":3,"delete":0,"area":0.0000967930549800304,"is_suspect":false,"harmful":null,"checked":false,"check_date":null,"host":"https://mapcomplete.org/climbing.html","theme":"climbing","answer":2,"locale":"nl","add-image":2,"change_within_25m":1,"change_within_5000m":1,"id":140906815}},{"id":140903262,"type":"Feature","geometry":{"type":"Polygon","coordinates":[[[11.6701461,48.067768],[11.6701461,48.067768],[11.6701461,48.067768],[11.6701461,48.067768],[11.6701461,48.067768]]]},"properties":{"check_user":null,"reasons":[],"tags":[],"features":[],"user":"The_Nickname","uid":"14742734","editor":"MapComplete 0.31.2","comment":"Adding data with #MapComplete for theme #cyclofix","comments_count":0,"source":"Not reported","imagery_used":"Not reported","date":"2023-09-06T16:32:03Z","reviewed_features":[],"tag_changes":{},"create":0,"modify":1,"delete":0,"area":0,"is_suspect":false,"harmful":null,"checked":false,"check_date":null,"host":"https://mapcomplete.org/cyclofix.html","theme":"cyclofix","answer":1,"locale":"de","id":140903262}},{"id":140902981,"type":"Feature","geometry":{"type":"Polygon","coordinates":[[[3.2249614,44.1938045],[3.2256693,44.1938045],[3.2256693,44.1942026],[3.2249614,44.1942026],[3.2249614,44.1938045]]]},"properties":{"check_user":null,"reasons":[],"tags":[],"features":[],"user":"Pieter Vander Vennet","uid":"3818858","editor":"MapComplete 0.31.2","comment":"Adding data with #MapComplete for theme #climbing","comments_count":0,"source":"Not reported","imagery_used":"Not reported","date":"2023-09-06T16:25:22Z","reviewed_features":[],"tag_changes":{},"create":4,"modify":1,"delete":0,"area":2.81814989998573e-7,"is_suspect":false,"harmful":null,"checked":false,"check_date":null,"host":"https://mapcomplete.org/climbing.html","theme":"climbing","locale":"nl","change_within_25m":4,"id":140902981}},{"id":140901614,"type":"Feature","geometry":{"type":"Polygon","coordinates":[[[2.2683033,41.4778562],[2.2729413,41.4778562],[2.2729413,41.4833552],[2.2683033,41.4833552],[2.2683033,41.4778562]]]},"properties":{"check_user":null,"reasons":[{"id":40,"name":"New mapper"}],"tags":[],"features":[],"user":"drpicox","uid":"19740148","editor":"MapComplete 0.27.5","comment":"Adding data with #MapComplete for theme #https://llefia.org/arbres/mapcomplete1.json","comments_count":0,"source":"Not reported","imagery_used":"Not reported","date":"2023-09-06T15:56:09Z","reviewed_features":[],"tag_changes":{},"create":4,"modify":15,"delete":0,"area":0.0000255043620000013,"is_suspect":true,"harmful":null,"checked":false,"check_date":null,"host":"https://pietervdvn.github.io/mc/legacy/0.27.4/theme.html","theme":"https://llefia.org/arbres/mapcomplete1.json","answer":16,"locale":"ca","imagery":"osm","add-image":5,"id":140901614}},{"id":140898847,"type":"Feature","geometry":{"type":"Polygon","coordinates":[[[15.5767696,54.175716],[15.5767696,54.175716],[15.5767696,54.175716],[15.5767696,54.175716],[15.5767696,54.175716]]]},"properties":{"check_user":null,"reasons":[],"tags":[],"features":[],"user":"5R-MFT","uid":"3417876","editor":"MapComplete 0.31.2","comment":"Adding data with #MapComplete for theme #drinking_water","comments_count":0,"source":"Not reported","imagery_used":"Not reported","date":"2023-09-06T14:52:20Z","reviewed_features":[],"tag_changes":{},"create":0,"modify":2,"delete":0,"area":0,"is_suspect":false,"harmful":null,"checked":false,"check_date":null,"host":"https://mapcomplete.org/drinking_water.html","theme":"drinking_water","answer":1,"locale":"de","add-image":1,"change_within_25m":1,"id":140898847}},{"id":140898626,"type":"Feature","geometry":{"type":"Polygon","coordinates":[[[15.5748763,54.1753759],[15.5748763,54.1753759],[15.5748763,54.1753759],[15.5748763,54.1753759],[15.5748763,54.1753759]]]},"properties":{"check_user":null,"reasons":[],"tags":[],"features":[],"user":"5R-MFT","uid":"3417876","editor":"MapComplete 0.31.2","comment":"Adding data with #MapComplete for theme #hailhydrant","comments_count":0,"source":"Not reported","imagery_used":"Not reported","date":"2023-09-06T14:47:03Z","reviewed_features":[],"tag_changes":{},"create":0,"modify":1,"delete":0,"area":0,"is_suspect":false,"harmful":null,"checked":false,"check_date":null,"host":"https://mapcomplete.org/hailhydrant.html","theme":"hailhydrant","locale":"de","add-image":1,"change_within_25m":1,"id":140898626}},{"id":140897868,"type":"Feature","geometry":{"type":"Polygon","coordinates":[[[15.5753545,54.1769855],[15.5754144,54.1769855],[15.5754144,54.177022],[15.5753545,54.177022],[15.5753545,54.1769855]]]},"properties":{"check_user":null,"reasons":[],"tags":[],"features":[],"user":"5R-MFT","uid":"3417876","editor":"MapComplete 0.31.2","comment":"Adding data with #MapComplete for theme #toilets","comments_count":0,"source":"Not reported","imagery_used":"Not reported","date":"2023-09-06T14:27:25Z","reviewed_features":[],"tag_changes":{},"create":0,"modify":2,"delete":0,"area":2.1863500000171e-9,"is_suspect":false,"harmful":null,"checked":false,"check_date":null,"host":"https://mapcomplete.org/toilets.html","theme":"toilets","answer":3,"locale":"de","add-image":1,"change_within_25m":1,"id":140897868}},{"id":140894180,"type":"Feature","geometry":{"type":"Polygon","coordinates":[[[4.3359862,50.8372009],[4.3405821,50.8372009],[4.3405821,50.8388744],[4.3359862,50.8388744],[4.3359862,50.8372009]]]},"properties":{"check_user":null,"reasons":[],"tags":[],"features":[],"user":"Kalepom","uid":"392288","editor":"MapComplete 0.31.2","comment":"Adding data with #MapComplete for theme #etymology","comments_count":0,"source":"Not reported","imagery_used":"Not reported","date":"2023-09-06T12:49:27Z","reviewed_features":[],"tag_changes":{},"create":0,"modify":8,"delete":0,"area":0.00000769123865001169,"is_suspect":false,"harmful":null,"checked":false,"check_date":null,"host":"https://mapcomplete.org/etymology.html","theme":"etymology","answer":7,"locale":"fr","add-image":1,"id":140894180}},{"id":140894004,"type":"Feature","geometry":{"type":"Polygon","coordinates":[[[16.13547,54.1778015],[16.13547,54.1778015],[16.13547,54.1778015],[16.13547,54.1778015],[16.13547,54.1778015]]]},"properties":{"check_user":null,"reasons":[],"tags":[],"features":[],"user":"5R-MFT","uid":"3417876","editor":"MapComplete 0.31.2","comment":"Adding data with #MapComplete for theme #postboxes","comments_count":0,"source":"Not reported","imagery_used":"Not reported","date":"2023-09-06T12:44:43Z","reviewed_features":[],"tag_changes":{},"create":0,"modify":1,"delete":0,"area":0,"is_suspect":false,"harmful":null,"checked":false,"check_date":null,"host":"https://mapcomplete.org/cyclofix.html","theme":"postboxes","answer":4,"locale":"de","add-image":2,"change_within_25m":2,"id":140894004}},{"id":140894003,"type":"Feature","geometry":{"type":"Polygon","coordinates":[[[16.1353114,54.1777075],[16.1353114,54.1777075],[16.1353114,54.1777075],[16.1353114,54.1777075],[16.1353114,54.1777075]]]},"properties":{"check_user":null,"reasons":[],"tags":[],"features":[],"user":"5R-MFT","uid":"3417876","editor":"MapComplete 0.31.2","comment":"Adding data with #MapComplete for theme #cyclofix","comments_count":0,"source":"Not reported","imagery_used":"Not reported","date":"2023-09-06T12:44:43Z","reviewed_features":[],"tag_changes":{},"create":1,"modify":0,"delete":0,"area":0,"is_suspect":false,"harmful":null,"checked":false,"check_date":null,"host":"https://mapcomplete.org/cyclofix.html","theme":"cyclofix","answer":5,"locale":"de","add-image":1,"change_over_5000m":1,"id":140894003}},{"id":140893618,"type":"Feature","geometry":{"type":"Polygon","coordinates":[[[4.3420589,50.8377385],[4.3420589,50.8377385],[4.3420589,50.8377385],[4.3420589,50.8377385],[4.3420589,50.8377385]]]},"properties":{"check_user":null,"reasons":[],"tags":[],"features":[],"user":"Kalepom","uid":"392288","editor":"MapComplete 0.31.2","comment":"Adding data with #MapComplete for theme #artwork","comments_count":0,"source":"Not reported","imagery_used":"Not reported","date":"2023-09-06T12:33:15Z","reviewed_features":[],"tag_changes":{},"create":0,"modify":1,"delete":0,"area":0,"is_suspect":false,"harmful":null,"checked":false,"check_date":null,"host":"https://mapcomplete.org/artwork.html","theme":"artwork","answer":1,"locale":"fr","id":140893618}},{"id":140893594,"type":"Feature","geometry":{"type":"Polygon","coordinates":[[[4.3420589,50.8377385],[4.3420589,50.8377385],[4.3420589,50.8377385],[4.3420589,50.8377385],[4.3420589,50.8377385]]]},"properties":{"check_user":null,"reasons":[],"tags":[],"features":[],"user":"Kalepom","uid":"392288","editor":"MapComplete 0.31.2","comment":"Adding data with #MapComplete for theme #artwork","comments_count":0,"source":"Not reported","imagery_used":"Not reported","date":"2023-09-06T12:32:46Z","reviewed_features":[],"tag_changes":{},"create":0,"modify":1,"delete":0,"area":0,"is_suspect":false,"harmful":null,"checked":false,"check_date":null,"host":"https://mapcomplete.org/artwork.html","theme":"artwork","locale":"fr","add-image":1,"id":140893594}},{"id":140893530,"type":"Feature","geometry":{"type":"Polygon","coordinates":[[[3.2272043,44.1957037],[3.2272043,44.1957037],[3.2272043,44.1957037],[3.2272043,44.1957037],[3.2272043,44.1957037]]]},"properties":{"check_user":null,"reasons":[],"tags":[],"features":[],"user":"Pieter Vander Vennet","uid":"3818858","editor":"MapComplete 0.31.2","comment":"Adding data with #MapComplete for theme #climbing","comments_count":0,"source":"Not reported","imagery_used":"Not reported","date":"2023-09-06T12:31:21Z","reviewed_features":[],"tag_changes":{},"create":0,"modify":1,"delete":0,"area":0,"is_suspect":false,"harmful":null,"checked":false,"check_date":null,"host":"https://mapcomplete.org/climbing.html","theme":"climbing","locale":"nl","add-image":1,"change_within_25m":1,"id":140893530}},{"id":140892852,"type":"Feature","geometry":{"type":"Polygon","coordinates":[[[19.0566813,47.4960384],[19.0595298,47.4960384],[19.0595298,47.4973968],[19.0566813,47.4973968],[19.0566813,47.4960384]]]},"properties":{"check_user":null,"reasons":[],"tags":[],"features":[],"user":"Koen Rijnsent","uid":"4569696","editor":"MapComplete 0.31.2","comment":"Adding data with #MapComplete for theme #artwork","comments_count":0,"source":"Not reported","imagery_used":"Not reported","date":"2023-09-06T12:17:36Z","reviewed_features":[],"tag_changes":{},"create":2,"modify":4,"delete":0,"area":0.00000386940239998077,"is_suspect":false,"harmful":null,"checked":false,"check_date":null,"host":"https://mapcomplete.org/artwork","theme":"artwork","answer":1,"locale":"en","add-image":4,"change_within_25m":2,"change_within_50m":1,"change_within_500m":3,"id":140892852}},{"id":140890112,"type":"Feature","geometry":{"type":"Polygon","coordinates":[[[3.226806,44.1947159],[3.2278106,44.1947159],[3.2278106,44.19629],[3.226806,44.19629],[3.226806,44.1947159]]]},"properties":{"check_user":null,"reasons":[],"tags":[],"features":[],"user":"Pieter Vander Vennet","uid":"3818858","editor":"MapComplete 0.31.2","comment":"Adding data with #MapComplete for theme #climbing","comments_count":0,"source":"Not reported","imagery_used":"Not reported","date":"2023-09-06T11:13:59Z","reviewed_features":[],"tag_changes":{},"create":2,"modify":4,"delete":0,"area":0.00000158134085999969,"is_suspect":false,"harmful":null,"checked":false,"check_date":null,"host":"https://mapcomplete.org/climbing.html","theme":"climbing","answer":6,"locale":"nl","add-image":1,"change_within_25m":2,"id":140890112}},{"id":140890072,"type":"Feature","geometry":{"type":"Polygon","coordinates":[[[3.2269172,44.1957694],[3.2269172,44.1957694],[3.2269172,44.1957694],[3.2269172,44.1957694],[3.2269172,44.1957694]]]},"properties":{"check_user":null,"reasons":[],"tags":[],"features":[],"user":"Pieter Vander Vennet","uid":"3818858","editor":"MapComplete 0.31.2","comment":"Adding data with #MapComplete for theme #climbing","comments_count":0,"source":"Not reported","imagery_used":"Not reported","date":"2023-09-06T11:13:15Z","reviewed_features":[],"tag_changes":{},"create":1,"modify":1,"delete":0,"area":0,"is_suspect":false,"harmful":null,"checked":false,"check_date":null,"host":"https://mapcomplete.org/climbing.html","theme":"climbing","locale":"nl","add-image":2,"change_over_5000m":1,"change_within_25m":1,"id":140890072}},{"id":140889100,"type":"Feature","geometry":{"type":"Polygon","coordinates":[[[16.4167238,54.4179949],[16.4167238,54.4179949],[16.4167238,54.4179949],[16.4167238,54.4179949],[16.4167238,54.4179949]]]},"properties":{"check_user":null,"reasons":[],"tags":[],"features":[],"user":"5R-MFT","uid":"3417876","editor":"MapComplete 0.31.2","comment":"Adding data with #MapComplete for theme #cyclofix","comments_count":0,"source":"Not reported","imagery_used":"Not reported","date":"2023-09-06T10:48:23Z","reviewed_features":[],"tag_changes":{},"create":0,"modify":1,"delete":0,"area":0,"is_suspect":false,"harmful":null,"checked":false,"check_date":null,"host":"https://mapcomplete.org/cyclofix.html","theme":"cyclofix","answer":4,"locale":"de","id":140889100}},{"id":140889037,"type":"Feature","geometry":{"type":"Polygon","coordinates":[[[16.2362754,54.2053893],[16.4163461,54.2053893],[16.4163461,54.4179768],[16.2362754,54.4179768],[16.2362754,54.2053893]]]},"properties":{"check_user":null,"reasons":[],"tags":[],"features":[],"user":"5R-MFT","uid":"3417876","editor":"MapComplete 0.31.2","comment":"Adding data with #MapComplete for theme #benches","comments_count":0,"source":"Not reported","imagery_used":"Not reported","date":"2023-09-06T10:46:32Z","reviewed_features":[],"tag_changes":{},"create":1,"modify":1,"delete":0,"area":0.0382807799362492,"is_suspect":false,"harmful":null,"checked":false,"check_date":null,"host":"https://mapcomplete.org/benches.html","theme":"benches","answer":6,"locale":"de","change_over_5000m":1,"id":140889037}},{"id":140888974,"type":"Feature","geometry":{"type":"Polygon","coordinates":[[[16.4162359,54.4176601],[16.4164408,54.4176601],[16.4164408,54.4179716],[16.4162359,54.4179716],[16.4162359,54.4176601]]]},"properties":{"check_user":null,"reasons":[],"tags":[],"features":[],"user":"5R-MFT","uid":"3417876","editor":"MapComplete 0.31.2","comment":"Adding data with #MapComplete for theme #parkings","comments_count":0,"source":"Not reported","imagery_used":"Not reported","date":"2023-09-06T10:44:40Z","reviewed_features":[],"tag_changes":{},"create":0,"modify":2,"delete":0,"area":6.38263500004442e-8,"is_suspect":false,"harmful":null,"checked":false,"check_date":null,"host":"https://mapcomplete.org/parkings.html","theme":"parkings","answer":3,"locale":"de","id":140888974}},{"id":140888817,"type":"Feature","geometry":{"type":"Polygon","coordinates":[[[16.4165224,54.4179009],[16.4165224,54.4179009],[16.4165224,54.4179009],[16.4165224,54.4179009],[16.4165224,54.4179009]]]},"properties":{"check_user":null,"reasons":[],"tags":[],"features":[],"user":"5R-MFT","uid":"3417876","editor":"MapComplete 0.31.2","comment":"Adding data with #MapComplete for theme #postboxes","comments_count":0,"source":"Not reported","imagery_used":"Not reported","date":"2023-09-06T10:40:19Z","reviewed_features":[],"tag_changes":{},"create":0,"modify":1,"delete":0,"area":0,"is_suspect":false,"harmful":null,"checked":false,"check_date":null,"host":"https://mapcomplete.org/postboxes.html","theme":"postboxes","locale":"de","add-image":1,"change_within_25m":1,"id":140888817}},{"id":140885671,"type":"Feature","geometry":{"type":"Polygon","coordinates":[[[10.7667892,46.626218],[10.7668686,46.626218],[10.7668686,46.6262365],[10.7667892,46.6262365],[10.7667892,46.626218]]]},"properties":{"check_user":null,"reasons":[],"tags":[],"features":[],"user":"M7746","uid":"15731387","editor":"MapComplete 0.31.2","comment":"Adding data with #MapComplete for theme #surveillance","comments_count":0,"source":"Not reported","imagery_used":"Not reported","date":"2023-09-06T09:09:18Z","reviewed_features":[],"tag_changes":{},"create":2,"modify":3,"delete":0,"area":1.46889999968784e-9,"is_suspect":false,"harmful":null,"checked":false,"check_date":null,"host":"https://mapcomplete.osm.be/surveillance.html","theme":"surveillance","answer":8,"locale":"de","change_over_5000m":1,"id":140885671}},{"id":140885384,"type":"Feature","geometry":{"type":"Polygon","coordinates":[[[2.1746415,41.4131232],[2.1746415,41.4131232],[2.1746415,41.4131232],[2.1746415,41.4131232],[2.1746415,41.4131232]]]},"properties":{"check_user":null,"reasons":[],"tags":[],"features":[],"user":"paunofu","uid":"13779940","editor":"MapComplete 0.31.2","comment":"Adding data with #MapComplete for theme #aed","comments_count":0,"source":"Not reported","imagery_used":"Not reported","date":"2023-09-06T09:03:07Z","reviewed_features":[],"tag_changes":{},"create":1,"modify":1,"delete":0,"area":0,"is_suspect":false,"harmful":null,"checked":false,"check_date":null,"host":"https://mapcomplete.org/aed.html","theme":"aed","answer":2,"locale":"ca","add-image":1,"change_over_5000m":1,"id":140885384}},{"id":140880846,"type":"Feature","geometry":{"type":"Polygon","coordinates":[[[2.2049216,41.447048],[2.2049216,41.447048],[2.2049216,41.447048],[2.2049216,41.447048],[2.2049216,41.447048]]]},"properties":{"check_user":null,"reasons":[],"tags":[],"features":[],"user":"Toni Serra","uid":"3859465","editor":"MapComplete 0.31.2","comment":"Adding data with #MapComplete for theme #artwork","comments_count":0,"source":"Not reported","imagery_used":"Not reported","date":"2023-09-06T07:24:06Z","reviewed_features":[],"tag_changes":{},"create":1,"modify":1,"delete":0,"area":0,"is_suspect":false,"harmful":null,"checked":false,"check_date":null,"host":"https://mapcomplete.osm.be/artwork.html","theme":"artwork","answer":1,"locale":"ca","add-image":1,"change_over_5000m":1,"id":140880846}},{"id":140876238,"type":"Feature","geometry":{"type":"Polygon","coordinates":[[[4.8799336,51.3040053],[4.9246615,51.3040053],[4.9246615,51.3146371],[4.8799336,51.3146371],[4.8799336,51.3040053]]]},"properties":{"check_user":null,"reasons":[],"tags":[],"features":[],"user":"user_3232","uid":"3232","editor":"MapComplete 0.31.2","comment":"Adding data with #MapComplete for theme #healthcare","comments_count":0,"source":"Not reported","imagery_used":"Not reported","date":"2023-09-06T04:59:39Z","reviewed_features":[],"tag_changes":{},"create":2,"modify":3,"delete":0,"area":0.000475538087219942,"is_suspect":false,"harmful":null,"checked":false,"check_date":null,"host":"https://mapcomplete.org/healthcare","theme":"healthcare","answer":5,"locale":"en-US","id":140876238}},{"id":140872923,"type":"Feature","geometry":{"type":"Polygon","coordinates":[[[-74.8049212,41.2514639],[-74.7923246,41.2514639],[-74.7923246,41.2862384],[-74.8049212,41.2862384],[-74.8049212,41.2514639]]]},"properties":{"check_user":null,"reasons":[],"tags":[],"features":[],"user":"stn8188","uid":"2438156","editor":"MapComplete 0.31.2","comment":"Adding data with #MapComplete for theme #personal","comments_count":0,"source":"Not reported","imagery_used":"Not reported","date":"2023-09-06T01:21:28Z","reviewed_features":[],"tag_changes":{},"create":0,"modify":6,"delete":0,"area":0.000438040466699879,"is_suspect":false,"harmful":null,"checked":false,"check_date":null,"host":"https://mapcomplete.org/personal","theme":"personal","answer":7,"locale":"en","id":140872923}},{"id":140872700,"type":"Feature","geometry":{"type":"Polygon","coordinates":[[[170.4869927,-45.9117904],[170.5315705,-45.9117904],[170.5315705,-45.8846391],[170.4869927,-45.8846391],[170.4869927,-45.9117904]]]},"properties":{"check_user":null,"reasons":[{"id":40,"name":"New mapper"}],"tags":[],"features":[],"user":"jayde-cohen","uid":"20182454","editor":"MapComplete 0.31.2","comment":"Adding data with #MapComplete for theme #food","comments_count":0,"source":"Not reported","imagery_used":"Not reported","date":"2023-09-06T01:06:05Z","reviewed_features":[],"tag_changes":{},"create":0,"modify":6,"delete":0,"area":0.00121034522113958,"is_suspect":true,"harmful":null,"checked":false,"check_date":null,"host":"https://mapcomplete.org/food.html","theme":"food","answer":6,"locale":"en","id":140872700}},{"id":140872676,"type":"Feature","geometry":{"type":"Polygon","coordinates":[[[170.4900239,-45.9111909],[170.4900239,-45.9111909],[170.4900239,-45.9111909],[170.4900239,-45.9111909],[170.4900239,-45.9111909]]]},"properties":{"check_user":null,"reasons":[{"id":40,"name":"New mapper"}],"tags":[],"features":[],"user":"jayde-cohen","uid":"20182454","editor":"MapComplete 0.31.2","comment":"Adding data with #MapComplete for theme #food","comments_count":0,"source":"Not reported","imagery_used":"Not reported","date":"2023-09-06T01:04:49Z","reviewed_features":[],"tag_changes":{},"create":0,"modify":2,"delete":0,"area":0,"is_suspect":true,"harmful":null,"checked":false,"check_date":null,"host":"https://mapcomplete.org/food.html","theme":"food","answer":2,"locale":"en","id":140872676}},{"id":140872652,"type":"Feature","geometry":{"type":"Polygon","coordinates":[[[170.4903261,-45.9115748],[170.4903261,-45.9115748],[170.4903261,-45.9115748],[170.4903261,-45.9115748],[170.4903261,-45.9115748]]]},"properties":{"check_user":null,"reasons":[{"id":40,"name":"New mapper"}],"tags":[],"features":[],"user":"jayde-cohen","uid":"20182454","editor":"MapComplete 0.31.2","comment":"Adding data with #MapComplete for theme #food","comments_count":0,"source":"Not reported","imagery_used":"Not reported","date":"2023-09-06T01:03:27Z","reviewed_features":[],"tag_changes":{},"create":0,"modify":1,"delete":0,"area":0,"is_suspect":true,"harmful":null,"checked":false,"check_date":null,"host":"https://mapcomplete.org/food.html","theme":"food","answer":1,"locale":"en","id":140872652}},{"id":140872646,"type":"Feature","geometry":{"type":"Polygon","coordinates":[[[170.4903261,-45.9115748],[170.4903261,-45.9115748],[170.4903261,-45.9115748],[170.4903261,-45.9115748],[170.4903261,-45.9115748]]]},"properties":{"check_user":null,"reasons":[{"id":40,"name":"New mapper"}],"tags":[],"features":[],"user":"jayde-cohen","uid":"20182454","editor":"MapComplete 0.31.2","comment":"Adding data with #MapComplete for theme #food","comments_count":0,"source":"Not reported","imagery_used":"Not reported","date":"2023-09-06T01:02:58Z","reviewed_features":[],"tag_changes":{},"create":0,"modify":1,"delete":0,"area":0,"is_suspect":true,"harmful":null,"checked":false,"check_date":null,"host":"https://mapcomplete.org/food.html","theme":"food","answer":1,"locale":"en","id":140872646}},{"id":140872643,"type":"Feature","geometry":{"type":"Polygon","coordinates":[[[170.4903261,-45.9115748],[170.4903261,-45.9115748],[170.4903261,-45.9115748],[170.4903261,-45.9115748],[170.4903261,-45.9115748]]]},"properties":{"check_user":null,"reasons":[{"id":40,"name":"New mapper"}],"tags":[],"features":[],"user":"jayde-cohen","uid":"20182454","editor":"MapComplete 0.31.2","comment":"Adding data with #MapComplete for theme #food","comments_count":0,"source":"Not reported","imagery_used":"Not reported","date":"2023-09-06T01:02:41Z","reviewed_features":[],"tag_changes":{},"create":0,"modify":1,"delete":0,"area":0,"is_suspect":true,"harmful":null,"checked":false,"check_date":null,"host":"https://mapcomplete.org/food.html","theme":"food","answer":1,"locale":"en","id":140872643}},{"id":140872094,"type":"Feature","geometry":{"type":"Polygon","coordinates":[[[170.456849,-45.9026666],[170.4572253,-45.9026666],[170.4572253,-45.9024587],[170.456849,-45.9024587],[170.456849,-45.9026666]]]},"properties":{"check_user":null,"reasons":[{"id":40,"name":"New mapper"}],"tags":[],"features":[],"user":"jayde-cohen","uid":"20182454","editor":"MapComplete 0.31.2","comment":"Adding data with #MapComplete for theme #cafes_and_pubs","comments_count":0,"source":"Not reported","imagery_used":"Not reported","date":"2023-09-06T00:19:01Z","reviewed_features":[],"tag_changes":{},"create":0,"modify":2,"delete":0,"area":7.8232770002317e-8,"is_suspect":true,"harmful":null,"checked":false,"check_date":null,"host":"https://mapcomplete.org/cafes_and_pubs.html","theme":"cafes_and_pubs","answer":2,"locale":"en","id":140872094}},{"id":140872086,"type":"Feature","geometry":{"type":"Polygon","coordinates":[[[170.456849,-45.9026666],[170.4572253,-45.9026666],[170.4572253,-45.9024587],[170.456849,-45.9024587],[170.456849,-45.9026666]]]},"properties":{"check_user":null,"reasons":[{"id":40,"name":"New mapper"}],"tags":[],"features":[],"user":"jayde-cohen","uid":"20182454","editor":"MapComplete 0.31.2","comment":"Adding data with #MapComplete for theme #cafes_and_pubs","comments_count":0,"source":"Not reported","imagery_used":"Not reported","date":"2023-09-06T00:18:13Z","reviewed_features":[],"tag_changes":{},"create":0,"modify":1,"delete":0,"area":7.8232770002317e-8,"is_suspect":true,"harmful":null,"checked":false,"check_date":null,"host":"https://mapcomplete.org/cafes_and_pubs.html","theme":"cafes_and_pubs","answer":1,"locale":"en","id":140872086}}]